enkanetworkcard/enc_error.py
enkanetworkcard/encbanner.py
enkanetworkcard/src/assets/constant/ANEMO.png
enkanetworkcard/src/assets/constant/CLOSED.png
enkanetworkcard/src/assets/constant/CLOSED_BG.png
enkanetworkcard/src/assets/constant/CONSTATN_BG.png
enkanetworkcard/src/assets/constant/CRYO.png
enkanetworkcard/src/assets/constant/DENDRO.png
enkanetworkcard/src/assets/constant/ELECTRO.png
enkanetworkcard/src/assets/constant/ERROR.png
enkanetworkcard/src/assets/constant/GEO.png
enkanetworkcard/src/assets/constant/GYDRO.png
enkanetworkcard/src/assets/constant/PYRO.png
enkanetworkcard/src/assets/elementColor/ELEC_ADD_HURT.png
enkanetworkcard/src/assets/elementColor/FIRE_ADD_HURT.png
enkanetworkcard/src/assets/elementColor/GRASS_ADD_HURT.png
enkanetworkcard/src/assets/elementColor/ICE_ADD_HURT.png
enkanetworkcard/src/assets/elementColor/ROCK_ADD_HURT.png
enkanetworkcard/src/assets/elementColor/WATER_ADD_HURT.png
enkanetworkcard/src/assets/elementColor/WIND_ADD_HURT.png
enkanetworkcard/src/assets/font/Genshin_Impact.ttf
enkanetworkcard/src/assets/icon/ANEMO.png
enkanetworkcard/src/assets/icon/ARTIFACT.png
enkanetworkcard/src/assets/icon/ATTACK.png
enkanetworkcard/src/assets/icon/ATTACK_PERCENT.png
enkanetworkcard/src/assets/icon/CHARGE_EFFICIENCY.png
enkanetworkcard/src/assets/icon/CRITICAL.png
enkanetworkcard/src/assets/icon/CRITICAL_HURT.png
enkanetworkcard/src/assets/icon/CRYO.png
enkanetworkcard/src/assets/icon/DEFENSE.png
enkanetworkcard/src/assets/icon/DEFENSE_PERCENT.png
enkanetworkcard/src/assets/icon/DENDRO.png
enkanetworkcard/src/assets/icon/ELECTRO.png
enkanetworkcard/src/assets/icon/FRIENDS.png
enkanetworkcard/src/assets/icon/GEO.png
enkanetworkcard/src/assets/icon/HEAL.png
enkanetworkcard/src/assets/icon/HEALED_ADD.png
enkanetworkcard/src/assets/icon/HP.png
enkanetworkcard/src/assets/icon/HP_PERCENT.png
enkanetworkcard/src/assets/icon/HYDRO.png
enkanetworkcard/src/assets/icon/MASTERY.png
enkanetworkcard/src/assets/icon/PHYSICAL_ADD_HURT.png
enkanetworkcard-0.3.1.dist-info/WHEEL
enkanetworkcard-0.3.1.dist-info/METADATA
enkanetworkcard-0.3.1.dist-info/RECORD
